{
  "queryFile": "./data/bigquery/queries/base_uploads_ip_by_hour.sql",
  "schemaFile": "./data/bigquery/schemas/base_uploads_ip.json",
  "outputTable": "bocoup_prod.base_uploads_ip_by_hour",
  "numberOfDays": 9,
  "dates": [
     "2009-01-15T00:00:00Z",
     "2010-01-01T00:00:00Z",
     "2011-01-01T00:00:00Z",
     "2012-01-01T00:00:00Z",
     "2013-01-01T00:00:00Z",
     "2014-01-01T00:00:00Z",
     "2015-01-01T00:00:00Z",
     "2016-01-01T00:00:00Z",
     "2016-07-15T00:00:00Z"
  ],

  "mergeTable": "bocoup_prod.base_merged_ip_by_hour",
  "mergeTableSchema": "./data/bigquery/schemas/all_ip.json",

  "withISPTable": "bocoup_prod.all_ip_by_hour",
  "withISPTableSchema": "./data/bigquery/schemas/all_ip.json"
}
